README.txt
setup.cfg
setup.py
collective/__init__.py
collective.types.topicgroup.egg-info/PKG-INFO
collective.types.topicgroup.egg-info/SOURCES.txt
collective.types.topicgroup.egg-info/dependency_links.txt
collective.types.topicgroup.egg-info/entry_points.txt
collective.types.topicgroup.egg-info/namespace_packages.txt
collective.types.topicgroup.egg-info/not-zip-safe
collective.types.topicgroup.egg-info/requires.txt
collective.types.topicgroup.egg-info/top_level.txt
collective/types/__init__.py
collective/types/topicgroup/__init__.py
collective/types/topicgroup/config.py
collective/types/topicgroup/configure.zcml
collective/types/topicgroup/content.py
collective/types/topicgroup/setuphandlers.py
collective/types/topicgroup/browser/__init__.py
collective/types/topicgroup/browser/collage.pt
collective/types/topicgroup/browser/collage.py
collective/types/topicgroup/browser/collage.zcml
collective/types/topicgroup/browser/configure.zcml
collective/types/topicgroup/browser/folder.py
collective/types/topicgroup/browser/folder_detail.pt
collective/types/topicgroup/browser/page_wrapper.pt
collective/types/topicgroup/browser/page_wrapper.py
collective/types/topicgroup/browser/topicgroup_icon.gif
collective/types/topicgroup/browser/util.py
collective/types/topicgroup/profiles/default/factorytool.xml
collective/types/topicgroup/profiles/default/import_steps.xml
collective/types/topicgroup/profiles/default/metadata.xml
collective/types/topicgroup/profiles/default/types.xml
collective/types/topicgroup/profiles/default/types/collective.types.TopicGroup.xml
collective/types/topicgroup/tests/__init__.py
collective/types/topicgroup/tests/base.py
collective/types/topicgroup/tests/test_doctests.py
collective/types/topicgroup/tests/test_setup.py
collective/types/topicgroup/tests/test_topicgroup.py
collective/types/topicgroup/tests/topicgroup.txt
docs/CUSTOMIZATION.txt
docs/HISTORY.txt
docs/INSTALL.txt
docs/LICENSE.GPL
docs/LICENSE.txt
docs/README.txt